sqlfingerprint/__init__.py
sqlfingerprint/core.py
sqlfingerprint/exceptions.py
sqlfingerprint/py.typed
sqlfingerprint-0.1.0.dist-info/METADATA
sqlfingerprint-0.1.0.dist-info/WHEEL
sqlfingerprint-0.1.0.dist-info/licenses/LICENSE
sqlfingerprint-0.1.0.dist-info/RECORD
