Metadata-Version: 2.4
Name: sqlfingerprint
Version: 0.1.0
Summary: Generate unique fingerprints for SQL queries
Project-URL: Homepage, https://github.com/yinhaox/sqlfingerprint
Author-email: yinhaox <yinhao0226@gmail.com>
License: MIT License
License-File: LICENSE
Classifier: Intended Audience :: Developers
Classifier: License :: OSI Approved :: MIT License
Classifier: Operating System :: OS Independent
Classifier: Programming Language :: Python :: 3
Classifier: Topic :: Database
Classifier: Topic :: Software Development :: Libraries :: Python Modules
Requires-Python: >=3.8
Requires-Dist: sqlparse>=0.5.3
